[
  {
    "slug": "ban-giu-am-chen-dia",
    "url_path": "/danh-muc-san-pham/ban-giu-am-chen-dia/",
    "post_type": "term",
    "post_status": "publish",
    "post_date": "",
    "modified": "",
    "featured_image_src": "https://saigonhoreca.vn/wp-content/uploads/2024/04/tu-ham-nong-thuc-an.jpg",
    "featured_image_alt": "",
    "canonical": "",
    "taxonomy": "product_category",
    "name": "Bàn giữ ấm chén dĩa - Tủ sấy chén",
    "description": ""
  },
  {
    "slug": "he-thong-hut-khoi",
    "url_path": "/danh-muc-san-pham/he-thong-hut-khoi/",
    "post_type": "term",
    "post_status": "publish",
    "post_date": "",
    "modified": "",
    "featured_image_src": "https://saigonhoreca.vn/wp-content/uploads/2023/12/he-thong-hut-khoi.jpg",
    "featured_image_alt": "",
    "canonical": "",
    "taxonomy": "product_category",
    "name": "Hệ Thống Hút Khói Bếp Công Nghiệp",
    "description": ""
  },
  {
    "slug": "he-thong-hut-khoi-cap-khi-tuoi-bep-nha-hang",
    "url_path": "/danh-muc-san-pham/he-thong-hut-khoi-cap-khi-tuoi-bep-nha-hang/",
    "post_type": "term",
    "post_status": "publish",
    "post_date": "",
    "modified": "",
    "featured_image_src": "https://saigonhoreca.vn/wp-content/uploads/2024/04/he-thong-hut-khoi-cap-khi-tuoi.jpg",
    "featured_image_alt": "hệ thống hút khói, cấp khí tươi bếp nhà hàng",
    "canonical": "",
    "taxonomy": "product_category",
    "name": "Hệ thống hút khói, cấp khí tươi bếp nhà hàng",
    "description": ""
  },
  {
    "slug": "may-lam-da-cong-nghiep",
    "url_path": "/danh-muc-san-pham/may-lam-da-cong-nghiep/",
    "post_type": "term",
    "post_status": "publish",
    "post_date": "",
    "modified": "",
    "featured_image_src": "https://saigonhoreca.vn/wp-content/uploads/2023/12/may-lam-da.jpg",
    "featured_image_alt": "Máy làm đá công nghiệp",
    "canonical": "",
    "taxonomy": "product_category",
    "name": "Máy Làm Đá Công Nghiệp",
    "description": ""
  },
  {
    "slug": "may-lam-da-vien",
    "url_path": "/danh-muc-san-pham/may-lam-da-vien/",
    "post_type": "term",
    "post_status": "publish",
    "post_date": "",
    "modified": "",
    "featured_image_src": "https://saigonhoreca.vn/wp-content/uploads/2023/12/may-lam-da.jpg",
    "featured_image_alt": "Máy làm đá công nghiệp",
    "canonical": "",
    "taxonomy": "product_category",
    "name": "Máy Làm Đá Viên",
    "description": ""
  },
  {
    "slug": "may-rua-ly-chen",
    "url_path": "/danh-muc-san-pham/may-rua-ly-chen/",
    "post_type": "term",
    "post_status": "publish",
    "post_date": "",
    "modified": "",
    "featured_image_src": "https://saigonhoreca.vn/wp-content/uploads/2024/04/may-rua-ly-chen.jpg",
    "featured_image_alt": "",
    "canonical": "",
    "taxonomy": "product_category",
    "name": "Máy rửa ly chén",
    "description": ""
  },
  {
    "slug": "bep-chien-cong-nghiep",
    "url_path": "/danh-muc-san-pham/thiet-bi-bep-cong-nghiep/bep-chien-cong-nghiep/",
    "post_type": "term",
    "post_status": "publish",
    "post_date": "",
    "modified": "",
    "featured_image_src": "https://saigonhoreca.vn/wp-content/uploads/2023/12/bep-chien-cong-nghiep.jpg",
    "featured_image_alt": "Bếp chiên công nghiệp",
    "canonical": "",
    "taxonomy": "product_category",
    "name": "Bếp Chiên Công Nghiệp",
    "description": ""
  },
  {
    "slug": "bep-gas-cong-nghiep",
    "url_path": "/danh-muc-san-pham/thiet-bi-bep-cong-nghiep/bep-gas-cong-nghiep/",
    "post_type": "term",
    "post_status": "publish",
    "post_date": "",
    "modified": "",
    "featured_image_src": "https://saigonhoreca.vn/wp-content/uploads/2023/12/bep-gas-cong-nghiep.jpg",
    "featured_image_alt": "",
    "canonical": "",
    "taxonomy": "product_category",
    "name": "Bếp Gas Công Nghiệp",
    "description": ""
  },
  {
    "slug": "bep-nuong-than-nhan-tao",
    "url_path": "/danh-muc-san-pham/thiet-bi-bep-cong-nghiep/bep-nuong-than-nhan-tao/",
    "post_type": "term",
    "post_status": "publish",
    "post_date": "",
    "modified": "",
    "featured_image_src": "https://saigonhoreca.vn/wp-content/uploads/2023/12/bep-nuong-than-nhan-tao.jpg",
    "featured_image_alt": "Bếp nướng than nhân tạo",
    "canonical": "",
    "taxonomy": "product_category",
    "name": "Bếp Nướng Than Nhân Tạo",
    "description": ""
  },
  {
    "slug": "thiet-bi-bep-cong-nghiep",
    "url_path": "/danh-muc-san-pham/thiet-bi-bep-cong-nghiep/",
    "post_type": "term",
    "post_status": "publish",
    "post_date": "",
    "modified": "",
    "featured_image_src": "https://saigonhoreca.vn/wp-content/uploads/2023/12/thiet-bi-bep-cong-nghiep-1.jpg",
    "featured_image_alt": "Thiết bị bếp công nghiệp",
    "canonical": "",
    "taxonomy": "product_category",
    "name": "Thiết Bị Bếp Công Nghiệp",
    "description": ""
  },
  {
    "slug": "thiet-bi-bep-cong-nghiep-sgh",
    "url_path": "/danh-muc-san-pham/thiet-bi-bep-cong-nghiep-sgh/",
    "post_type": "term",
    "post_status": "publish",
    "post_date": "",
    "modified": "",
    "featured_image_src": "https://saigonhoreca.vn/wp-content/uploads/2023/12/bep-cong-nghiep.jpg",
    "featured_image_alt": "",
    "canonical": "",
    "taxonomy": "product_category",
    "name": "Thiết Bị Bếp Công Nghiệp Sài Gòn",
    "description": ""
  },
  {
    "slug": "bep-au-cong-nghiep",
    "url_path": "/danh-muc-san-pham/thiet-bi-bep-nha-hang-au/bep-au-cong-nghiep/",
    "post_type": "term",
    "post_status": "publish",
    "post_date": "",
    "modified": "",
    "featured_image_src": "https://saigonhoreca.vn/wp-content/uploads/2023/12/bep-au-cong-nghiep.jpg",
    "featured_image_alt": "",
    "canonical": "",
    "taxonomy": "product_category",
    "name": "Bếp Âu Công Nghiệp",
    "description": ""
  },
  {
    "slug": "bep-chien-nhung-cong-nghiep",
    "url_path": "/danh-muc-san-pham/thiet-bi-bep-nha-hang-au/bep-chien-nhung-cong-nghiep/",
    "post_type": "term",
    "post_status": "publish",
    "post_date": "",
    "modified": "",
    "featured_image_src": "https://saigonhoreca.vn/wp-content/uploads/2023/12/bep-chien-nhung.jpg",
    "featured_image_alt": "Bếp chiên nhúng",
    "canonical": "",
    "taxonomy": "product_category",
    "name": "Bếp Chiên Nhúng Công Nghiệp",
    "description": ""
  },
  {
    "slug": "bep-chien-phang-cong-nghiep",
    "url_path": "/danh-muc-san-pham/thiet-bi-bep-nha-hang-au/bep-chien-phang-cong-nghiep/",
    "post_type": "term",
    "post_status": "publish",
    "post_date": "",
    "modified": "",
    "featured_image_src": "https://saigonhoreca.vn/wp-content/uploads/2023/12/bep-chien-phang.jpg",
    "featured_image_alt": "Bếp chiên phẩng",
    "canonical": "",
    "taxonomy": "product_category",
    "name": "Bếp Chiên Phẳng Công Nghiệp",
    "description": ""
  },
  {
    "slug": "bep-dien-tu-cong-nghiep-thiet-bi-bep-nha-hang-au",
    "url_path": "/danh-muc-san-pham/thiet-bi-bep-nha-hang-au/bep-dien-tu-cong-nghiep-thiet-bi-bep-nha-hang-au/",
    "post_type": "term",
    "post_status": "publish",
    "post_date": "",
    "modified": "",
    "featured_image_src": "https://saigonhoreca.vn/wp-content/uploads/2024/04/bep-dien-tu-cong-nghiep.jpg",
    "featured_image_alt": "",
    "canonical": "",
    "taxonomy": "product_category",
    "name": "Bếp Điện Từ Công Nghiệp",
    "description": ""
  },
  {
    "slug": "bep-nuong-than-nhan-tao-thiet-bi-bep-nha-hang-au",
    "url_path": "/danh-muc-san-pham/thiet-bi-bep-nha-hang-au/bep-nuong-than-nhan-tao-thiet-bi-bep-nha-hang-au/",
    "post_type": "term",
    "post_status": "publish",
    "post_date": "",
    "modified": "",
    "featured_image_src": "https://saigonhoreca.vn/wp-content/uploads/2023/12/bep-nuong-than-nhan-tao.jpg",
    "featured_image_alt": "Bếp nướng than nhân tạo",
    "canonical": "",
    "taxonomy": "product_category",
    "name": "Bếp Nướng Than Nhân Tạo",
    "description": ""
  },
  {
    "slug": "thiet-bi-bep-nha-hang-au",
    "url_path": "/danh-muc-san-pham/thiet-bi-bep-nha-hang-au/",
    "post_type": "term",
    "post_status": "publish",
    "post_date": "",
    "modified": "",
    "featured_image_src": "https://saigonhoreca.vn/wp-content/uploads/2023/12/thiep-bi-bep-nha-hang-au.jpg",
    "featured_image_alt": "",
    "canonical": "",
    "taxonomy": "product_category",
    "name": "Thiết bị bếp nhà hàng Âu",
    "description": ""
  },
  {
    "slug": "thiet-bi-che-bien-thuc-pham",
    "url_path": "/danh-muc-san-pham/thiet-bi-che-bien-thuc-pham/",
    "post_type": "term",
    "post_status": "publish",
    "post_date": "",
    "modified": "",
    "featured_image_src": "https://saigonhoreca.vn/wp-content/uploads/2023/12/thiet-bi-che-bien-thuc-pham.jpg",
    "featured_image_alt": "Thiết bị chế biến thực phẩm",
    "canonical": "",
    "taxonomy": "product_category",
    "name": "Thiết Bị Chế Biến Thực Phẩm",
    "description": ""
  },
  {
    "slug": "lo-hap-nuong-da-nang",
    "url_path": "/danh-muc-san-pham/thiet-bi-che-bien-thuc-pham/lo-hap-nuong-da-nang/",
    "post_type": "term",
    "post_status": "publish",
    "post_date": "",
    "modified": "",
    "featured_image_src": "https://saigonhoreca.vn/wp-content/uploads/2023/12/lo-hap-nuong-da-nang.jpg",
    "featured_image_alt": "Lò hấp nướng đa năng",
    "canonical": "",
    "taxonomy": "product_category",
    "name": "Lò Hấp Nướng Đa Năng",
    "description": ""
  },
  {
    "slug": "lo-nuong-cong-nghiep",
    "url_path": "/danh-muc-san-pham/thiet-bi-che-bien-thuc-pham/lo-nuong-cong-nghiep/",
    "post_type": "term",
    "post_status": "publish",
    "post_date": "",
    "modified": "",
    "featured_image_src": "https://saigonhoreca.vn/wp-content/uploads/2023/12/lo-nuong-cong-nghiep.jpg",
    "featured_image_alt": "Lò nướng công nghiệp",
    "canonical": "",
    "taxonomy": "product_category",
    "name": "Lò Nướng Công Nghiệp",
    "description": ""
  },
  {
    "slug": "lo-vi-song-cong-nghiep",
    "url_path": "/danh-muc-san-pham/thiet-bi-che-bien-thuc-pham/lo-vi-song-cong-nghiep/",
    "post_type": "term",
    "post_status": "publish",
    "post_date": "",
    "modified": "",
    "featured_image_src": "https://saigonhoreca.vn/wp-content/uploads/2023/12/lo-vi-song-cong-nghiep.jpg",
    "featured_image_alt": "Lò vi sóng công nghiệp",
    "canonical": "",
    "taxonomy": "product_category",
    "name": "Lò Vi Sóng Công Nghiệp",
    "description": ""
  },
  {
    "slug": "may-hut-chan-khong",
    "url_path": "/danh-muc-san-pham/thiet-bi-che-bien-thuc-pham/may-hut-chan-khong/",
    "post_type": "term",
    "post_status": "publish",
    "post_date": "",
    "modified": "",
    "featured_image_src": "https://saigonhoreca.vn/wp-content/uploads/2023/12/may-hut-chan-khong.jpg",
    "featured_image_alt": "Máy hút chân không",
    "canonical": "",
    "taxonomy": "product_category",
    "name": "Máy Hút Chân Không",
    "description": ""
  },
  {
    "slug": "may-nau-cham-sous-vide",
    "url_path": "/danh-muc-san-pham/thiet-bi-che-bien-thuc-pham/may-nau-cham-sous-vide/",
    "post_type": "term",
    "post_status": "publish",
    "post_date": "",
    "modified": "",
    "featured_image_src": "https://saigonhoreca.vn/wp-content/uploads/2023/12/may-nau-cham-sous-vide.jpg",
    "featured_image_alt": "Máy nấu châm Sous Vide",
    "canonical": "",
    "taxonomy": "product_category",
    "name": "Máy Nấu Chậm Sous-Vide",
    "description": ""
  },
  {
    "slug": "tu-com-cong-nghiep",
    "url_path": "/danh-muc-san-pham/thiet-bi-che-bien-thuc-pham/tu-com-cong-nghiep/",
    "post_type": "term",
    "post_status": "publish",
    "post_date": "",
    "modified": "",
    "featured_image_src": "https://saigonhoreca.vn/wp-content/uploads/2024/04/tu-nau-com-cong-nghiep.jpg",
    "featured_image_alt": "",
    "canonical": "",
    "taxonomy": "product_category",
    "name": "Tủ Cơm Công Nghiệp",
    "description": ""
  },
  {
    "slug": "thiet-bi-inox-khac",
    "url_path": "/danh-muc-san-pham/thiet-bi-inox-khac/",
    "post_type": "term",
    "post_status": "publish",
    "post_date": "",
    "modified": "",
    "featured_image_src": "https://saigonhoreca.vn/wp-content/uploads/2023/12/thiet-bi-inox-khac.jpg",
    "featured_image_alt": "Thiết bị inox khác",
    "canonical": "",
    "taxonomy": "product_category",
    "name": "Thiết bị inox khác",
    "description": ""
  },
  {
    "slug": "thung-dung-da-inox",
    "url_path": "/danh-muc-san-pham/thiet-bi-inox-khac/thung-dung-da-inox/",
    "post_type": "term",
    "post_status": "publish",
    "post_date": "",
    "modified": "",
    "featured_image_src": "https://saigonhoreca.vn/wp-content/uploads/2023/12/thung-da-inox.jpg",
    "featured_image_alt": "Thùng đá inox",
    "canonical": "",
    "taxonomy": "product_category",
    "name": "Thùng Đựng Đá Inox",
    "description": ""
  },
  {
    "slug": "ban-dong-cong-nghiep",
    "url_path": "/danh-muc-san-pham/thiet-bi-lanh-cong-nghiep/ban-dong-cong-nghiep/",
    "post_type": "term",
    "post_status": "publish",
    "post_date": "",
    "modified": "",
    "featured_image_src": "https://saigonhoreca.vn/wp-content/uploads/2023/12/ban-dong.jpg",
    "featured_image_alt": "",
    "canonical": "",
    "taxonomy": "product_category",
    "name": "Bàn Đông Công Nghiệp",
    "description": ""
  },
  {
    "slug": "ban-lanh-salad-cong-nghiep",
    "url_path": "/danh-muc-san-pham/thiet-bi-lanh-cong-nghiep/ban-lanh-salad-cong-nghiep/",
    "post_type": "term",
    "post_status": "publish",
    "post_date": "",
    "modified": "",
    "featured_image_src": "https://saigonhoreca.vn/wp-content/uploads/2023/12/ban-lanh-salad-pizza.jpg",
    "featured_image_alt": "",
    "canonical": "",
    "taxonomy": "product_category",
    "name": "Bàn Lạnh Salad Công Nghiệp",
    "description": ""
  },
  {
    "slug": "ban-mat-cong-nghiep",
    "url_path": "/danh-muc-san-pham/thiet-bi-lanh-cong-nghiep/ban-mat-cong-nghiep/",
    "post_type": "term",
    "post_status": "publish",
    "post_date": "",
    "modified": "",
    "featured_image_src": "https://saigonhoreca.vn/wp-content/uploads/2023/12/ban-lanh-e1708739662806.jpg",
    "featured_image_alt": "Bàn mát công nghiệp",
    "canonical": "",
    "taxonomy": "product_category",
    "name": "Bàn Mát Công Nghiệp",
    "description": ""
  },
  {
    "slug": "thiet-bi-lanh-cong-nghiep",
    "url_path": "/danh-muc-san-pham/thiet-bi-lanh-cong-nghiep/",
    "post_type": "term",
    "post_status": "publish",
    "post_date": "",
    "modified": "",
    "featured_image_src": "https://saigonhoreca.vn/wp-content/uploads/2023/12/tu-cap-dong-bao-quan.jpg",
    "featured_image_alt": "Tủ cấp đông bảo quản",
    "canonical": "",
    "taxonomy": "product_category",
    "name": "Thiết bị lạnh công nghiệp",
    "description": ""
  },
  {
    "slug": "tu-bao-quan-trung-bay",
    "url_path": "/danh-muc-san-pham/thiet-bi-lanh-cong-nghiep/tu-bao-quan-trung-bay/",
    "post_type": "term",
    "post_status": "publish",
    "post_date": "",
    "modified": "",
    "featured_image_src": "https://saigonhoreca.vn/wp-content/uploads/2023/12/tu-bao-quan-tu-trung-bay.jpg",
    "featured_image_alt": "",
    "canonical": "",
    "taxonomy": "product_category",
    "name": "Tủ Bảo Quản, Trưng Bày",
    "description": ""
  },
  {
    "slug": "tu-cap-dong-nhanh-blast-chiller",
    "url_path": "/danh-muc-san-pham/thiet-bi-lanh-cong-nghiep/tu-cap-dong-nhanh-blast-chiller/",
    "post_type": "term",
    "post_status": "publish",
    "post_date": "",
    "modified": "",
    "featured_image_src": "https://saigonhoreca.vn/wp-content/uploads/2023/12/thiet-bi-cap-dong-nhanh.jpg",
    "featured_image_alt": "Thiết bị cấp đông nhanh",
    "canonical": "",
    "taxonomy": "product_category",
    "name": "Tủ Cấp Đông Nhanh Blast Chiller",
    "description": ""
  },
  {
    "slug": "tu-dong-cong-nghiep",
    "url_path": "/danh-muc-san-pham/thiet-bi-lanh-cong-nghiep/tu-dong-cong-nghiep/",
    "post_type": "term",
    "post_status": "publish",
    "post_date": "",
    "modified": "",
    "featured_image_src": "https://saigonhoreca.vn/wp-content/uploads/2023/12/tu-dong-cong-nghiep.jpg",
    "featured_image_alt": "Tủ đông công nghiệp",
    "canonical": "",
    "taxonomy": "product_category",
    "name": "Tủ Đông Công Nghiệp",
    "description": ""
  },
  {
    "slug": "tu-mat-cong-nghiep",
    "url_path": "/danh-muc-san-pham/thiet-bi-lanh-cong-nghiep/tu-mat-cong-nghiep/",
    "post_type": "term",
    "post_status": "publish",
    "post_date": "",
    "modified": "",
    "featured_image_src": "https://saigonhoreca.vn/wp-content/uploads/2023/12/tu-mat-cong-nghiep.jpg",
    "featured_image_alt": "Tủ mát công nghiệp",
    "canonical": "",
    "taxonomy": "product_category",
    "name": "Tủ Mát Công Nghiệp",
    "description": ""
  },
  {
    "slug": "thiet-bi-lanh-cong-nghiep-khac",
    "url_path": "/danh-muc-san-pham/thiet-bi-lanh-cong-nghiep-khac/",
    "post_type": "term",
    "post_status": "publish",
    "post_date": "",
    "modified": "",
    "featured_image_src": "https://saigonhoreca.vn/wp-content/uploads/2023/12/thiet-bi-cong-nghiep-khac.jpg",
    "featured_image_alt": "Thiết bị lạnh công nghiệp khác",
    "canonical": "",
    "taxonomy": "product_category",
    "name": "Thiết Bị Lạnh Công Nghiệp Khác",
    "description": ""
  },
  {
    "slug": "may-lam-da-cong-nghiep",
    "url_path": "/danh-muc-san-pham/thiet-bi-lanh-cong-nghiep-khac/may-lam-da-cong-nghiep/",
    "post_type": "term",
    "post_status": "publish",
    "post_date": "",
    "modified": "",
    "featured_image_src": "https://saigonhoreca.vn/wp-content/uploads/2023/12/may-lam-da.jpg",
    "featured_image_alt": "Máy làm đá công nghiệp",
    "canonical": "",
    "taxonomy": "product_category",
    "name": "Máy Làm Đá Công Nghiệp",
    "description": ""
  },
  {
    "slug": "may-lam-da-vien",
    "url_path": "/danh-muc-san-pham/thiet-bi-lanh-cong-nghiep-khac/may-lam-da-vien/",
    "post_type": "term",
    "post_status": "publish",
    "post_date": "",
    "modified": "",
    "featured_image_src": "https://saigonhoreca.vn/wp-content/uploads/2023/12/may-lam-da.jpg",
    "featured_image_alt": "Máy làm đá công nghiệp",
    "canonical": "",
    "taxonomy": "product_category",
    "name": "Máy Làm Đá Viên",
    "description": ""
  },
  {
    "slug": "thiet-bi-may-nau-cham-sous-vide",
    "url_path": "/danh-muc-san-pham/thiet-bi-may-nau-cham-sous-vide/",
    "post_type": "term",
    "post_status": "publish",
    "post_date": "",
    "modified": "",
    "featured_image_src": "https://saigonhoreca.vn/wp-content/uploads/2023/12/may-nau-cham-sous-vide.jpg",
    "featured_image_alt": "Máy nấu châm Sous Vide",
    "canonical": "",
    "taxonomy": "product_category",
    "name": "Máy Nấu Chậm Sous Vide",
    "description": ""
  },
  {
    "slug": "thiet-bi-quay-bar-cafe",
    "url_path": "/danh-muc-san-pham/thiet-bi-quay-bar-cafe/",
    "post_type": "term",
    "post_status": "publish",
    "post_date": "",
    "modified": "",
    "featured_image_src": "https://saigonhoreca.vn/wp-content/uploads/2023/12/may-pha-ca-phe.jpg",
    "featured_image_alt": "Thiết bị bar - cafe",
    "canonical": "",
    "taxonomy": "product_category",
    "name": "Thiết Bị Quầy Bar - Cafe",
    "description": ""
  },
  {
    "slug": "may-ep-trai-cay",
    "url_path": "/danh-muc-san-pham/thiet-bi-quay-bar-cafe/may-ep-trai-cay/",
    "post_type": "term",
    "post_status": "publish",
    "post_date": "",
    "modified": "",
    "featured_image_src": "https://saigonhoreca.vn/wp-content/uploads/2023/12/may-ep-trai-cay.jpg",
    "featured_image_alt": "",
    "canonical": "",
    "taxonomy": "product_category",
    "name": "Máy Ép Trái Cây",
    "description": ""
  }
]